baranomi/__init__.py
baranomi/pirates.py
baranomi-0.1.dist-info/LICENSE
baranomi-0.1.dist-info/METADATA
baranomi-0.1.dist-info/WHEEL
baranomi-0.1.dist-info/top_level.txt
baranomi-0.1.dist-info/RECORD
