Metadata-Version: 2.1
Name: baranomi
Version: 0.1
Summary: Split and join files.
Home-page: http://packages.python.org/an_example_pypi_project
Author: Kevin Hill
Author-email: kah.kevin.hill@gmail.com
License: BSD
Keywords: example documentation tutorial
Platform: UNKNOWN
Classifier: Development Status :: 3 - Alpha
Classifier: Topic :: Utilities
Classifier: License :: OSI Approved :: BSD License
